easytailwind/__init__.py
easytailwind/main.py
easytailwind-1.1.7.dist-info/METADATA
easytailwind-1.1.7.dist-info/WHEEL
easytailwind-1.1.7.dist-info/entry_points.txt
easytailwind-1.1.7.dist-info/top_level.txt
easytailwind-1.1.7.dist-info/RECORD
