Metadata-Version: 2.1
Name: easytailwind
Version: 1.1.7
Summary: A utility to set up Tailwind CSS in your Flask project.
Author: Sayed Afaq
Requires-Python: >=3.6
Requires-Dist: colorama
